{
  "coc.preferences.formatOnSaveFiletypes": ["*"],
  "diagnostic.displayByAle": true,
  "dialog.confirmKey": "<C-k>",
  "diagnostic.checkCurrentLine": true,
  "explorer.icon.enableNerdfont": true,
  "explorer.file.cdCommand": "cd",
  "explorer.width": 30,
  "eslint.autoFixOnSave": true,
  "eslint.packageManager": "yarn",
  "eslint.nodeEnv": "local",
  "npm.binPath": "yarn",
  "coc.preferences.currentFunctionSymbolAutoUpdate": true,
  "python.formatting.provider": "yapf",
  "list.insertMappings": {
    "<C-n>": "normal:j",
    "<C-p>": "normal:k"
  },
  "texlab.build.onSave": true,
  "texlab.auxDirectory": "./out",
  "texlab.build.args": []
}
